meent/__init__.py
meent/main.py
meent/nk_data/filmetrics/Al2O3.txt
meent/nk_data/filmetrics/Si.txt
meent/nk_data/filmetrics/Si3N4.txt
meent/nk_data/filmetrics/SiO2.txt
meent/nk_data/matlab/p_Si.mat
meent/on_jax/__init__.py
meent/on_jax/mee.py
meent/on_jax/emsolver/__init__.py
meent/on_jax/emsolver/_base.py
meent/on_jax/emsolver/convolution_matrix.py
meent/on_jax/emsolver/field_distribution.py
meent/on_jax/emsolver/fourier_analysis.py
meent/on_jax/emsolver/primitives.py
meent/on_jax/emsolver/rcwa.py
meent/on_jax/emsolver/scattering_method.py
meent/on_jax/emsolver/smm_util.py
meent/on_jax/emsolver/transfer_method.py
meent/on_jax/modeler/__init__.py
meent/on_jax/modeler/modeling.py
meent/on_jax/optimizer/__init__.py
meent/on_jax/optimizer/optimizer.py
meent/on_numpy/__init__.py
meent/on_numpy/mee.py
meent/on_numpy/emsolver/__init__.py
meent/on_numpy/emsolver/_base.py
meent/on_numpy/emsolver/convolution_matrix.py
meent/on_numpy/emsolver/field_distribution.py
meent/on_numpy/emsolver/fourier_analysis.py
meent/on_numpy/emsolver/primitives.py
meent/on_numpy/emsolver/rcwa.py
meent/on_numpy/emsolver/scattering_method.py
meent/on_numpy/emsolver/smm_util.py
meent/on_numpy/emsolver/transfer_method.py
meent/on_numpy/modeler/__init__.py
meent/on_numpy/modeler/modeling.py
meent/on_torch/__init__.py
meent/on_torch/mee.py
meent/on_torch/emsolver/__init__.py
meent/on_torch/emsolver/_base.py
meent/on_torch/emsolver/convolution_matrix.py
meent/on_torch/emsolver/field_distribution.py
meent/on_torch/emsolver/fourier_analysis.py
meent/on_torch/emsolver/primitives.py
meent/on_torch/emsolver/rcwa.py
meent/on_torch/emsolver/scattering_method.py
meent/on_torch/emsolver/smm_util.py
meent/on_torch/emsolver/transfer_method.py
meent/on_torch/modeler/__init__.py
meent/on_torch/modeler/modeling.py
meent/on_torch/optimizer/__init__.py
meent/on_torch/optimizer/optimizer.py
meent-0.12.0.dist-info/LICENSE
meent-0.12.0.dist-info/METADATA
meent-0.12.0.dist-info/WHEEL
meent-0.12.0.dist-info/top_level.txt
meent-0.12.0.dist-info/RECORD
